pydomjudge/__init__.py
pydomjudge/domjudge.py
pydomjudge/clients/__init__.py
pydomjudge/clients/access.py
pydomjudge/clients/accounts.py
pydomjudge/clients/awards.py
pydomjudge/clients/balloons.py
pydomjudge/clients/clarifications.py
pydomjudge/clients/client.py
pydomjudge/clients/contests.py
pydomjudge/clients/executables.py
pydomjudge/clients/general.py
pydomjudge/clients/groups.py
pydomjudge/clients/judgehosts.py
pydomjudge/clients/judgements.py
pydomjudge/clients/judgetypes.py
pydomjudge/clients/languages.py
pydomjudge/clients/metrics.py
pydomjudge/clients/organizations.py
pydomjudge/clients/problems.py
pydomjudge/clients/runs.py
pydomjudge/clients/scoreboards.py
pydomjudge/clients/submissions.py
pydomjudge/clients/teams.py
pydomjudge/clients/users.py
pydomjudge/models/__init__.py
pydomjudge/models/main.py
pydomjudge/models/request.py
pydomjudge/models/response.py
pydomjudge/models/shared.py
pydomjudge-0.1.1.dist-info/licenses/LICENSE
pydomjudge-0.1.1.dist-info/METADATA
pydomjudge-0.1.1.dist-info/WHEEL
pydomjudge-0.1.1.dist-info/top_level.txt
pydomjudge-0.1.1.dist-info/RECORD
