Metadata-Version: 2.4
Name: pydomjudge
Version: 0.1.1
Summary: A Python DOMJudge API wrapper
Author-email: xIvqn <xivqn@proton.me>
Project-URL: Homepage, https://github.com/xivqn/pydomjudge
Project-URL: Issues, https://github.com/xivqn/pydomjudge/issues
Classifier: Programming Language :: Python :: 3
Classifier: Operating System :: OS Independent
Requires-Python: >=3.8
License-File: LICENSE
Dynamic: license-file
